txt2image/__about__.py
txt2image/__init__.py
txt2image/basic.py
txt2image/misc.py
txt2image/quote.py
txt2image-0.0.1.dist-info/LICENSE
txt2image-0.0.1.dist-info/METADATA
txt2image-0.0.1.dist-info/WHEEL
txt2image-0.0.1.dist-info/top_level.txt
txt2image-0.0.1.dist-info/RECORD
