Metadata-Version: 2.1
Name: txt2image
Version: 0.0.1
Summary: Make add text to an image
Home-page: https://github.com/axju/txt2image
Author: Axel Juraske
Author-email: axel.juraske@short-report.de
License: MIT
Keywords: image text
Platform: UNKNOWN
Classifier: Intended Audience :: Developers
Classifier: Operating System :: OS Independent
Classifier: Programming Language :: Python
Classifier: Programming Language :: Python :: 3.5
Classifier: Programming Language :: Python :: 3.6
Classifier: Programming Language :: Python :: 3.7
Requires-Dist: pillow
